deepseek.py
assets/mq9_reaper_nsa_style.png
deepseeker-2.4.0.dist-info/METADATA
deepseeker-2.4.0.dist-info/WHEEL
deepseeker-2.4.0.dist-info/entry_points.txt
deepseeker-2.4.0.dist-info/top_level.txt
deepseeker-2.4.0.dist-info/RECORD
