Metadata-Version: 2.4
Name: deepseeker
Version: 2.4.0
Summary: DeepSeek AI-powered CLI agent with HITL guardrails for code assistance and automation
Author-email: Bo Shang <bo@shang.software>
License: MIT
Project-URL: Homepage, https://github.com/ErosolarAI/deepseeker
Project-URL: Repository, https://github.com/ErosolarAI/deepseeker
Project-URL: Issues, https://github.com/ErosolarAI/deepseeker/issues
Keywords: ai,cli,llm,deepseek,openai,anthropic,code-assistant,automation,developer-tools,guardrails,hitl
Classifier: Development Status :: 4 - Beta
Classifier: Environment :: Console
Classifier: Intended Audience :: Developers
Classifier: License :: OSI Approved :: MIT License
Classifier: Operating System :: OS Independent
Classifier: Programming Language :: Python :: 3
Classifier: Programming Language :: Python :: 3.10
Classifier: Programming Language :: Python :: 3.11
Classifier: Programming Language :: Python :: 3.12
Classifier: Topic :: Software Development
Classifier: Topic :: Utilities
Requires-Python: >=3.10
Requires-Dist: openai>=1.0.0
Requires-Dist: rich>=13.0.0
Provides-Extra: all
Requires-Dist: anthropic>=0.20.0; extra == "all"
Requires-Dist: google-generativeai>=0.3.0; extra == "all"
Requires-Dist: tavily-python>=0.3.0; extra == "all"
Provides-Extra: anthropic
Requires-Dist: anthropic>=0.20.0; extra == "anthropic"
Provides-Extra: google
Requires-Dist: google-generativeai>=0.3.0; extra == "google"
Provides-Extra: search
Requires-Dist: tavily-python>=0.3.0; extra == "search"
Provides-Extra: dev
Requires-Dist: pytest>=7.0.0; extra == "dev"
Requires-Dist: pytest-asyncio>=0.21.0; extra == "dev"
Requires-Dist: black>=23.0.0; extra == "dev"
Requires-Dist: ruff>=0.1.0; extra == "dev"
Requires-Dist: mypy>=1.0.0; extra == "dev"
